zotero_utils/__init__.py
zotero_utils/__main__.py
zotero_utils/commands.py
zotero_utils/Classes/creator.py
zotero_utils/Classes/item.py
zotero_utils/Classes/publisher.py
zotero_utils/Counts/counts.py
zotero_utils/Items/get_all_items.py
zotero_utils/Parse_PDFs/extract_references.py
zotero_utils/Parse_PDFs/pdf2md.py
zotero_utils/Visualizations/pie_chart.py
zotero_utils/Visualizations/stacked_bar_chart.py
zotero_utils/Visualizations/stem_plot.py
zotero_utils-0.1.2.dist-info/METADATA
zotero_utils-0.1.2.dist-info/WHEEL
zotero_utils-0.1.2.dist-info/entry_points.txt
zotero_utils-0.1.2.dist-info/RECORD
