Metadata-Version: 2.3
Name: zotero_utils
Version: 0.1.2
Summary: Tools to locally analyze a Zotero library.
Project-URL: Documentation, https://mtillman14.github.io/zotero_utils/
Project-URL: Repository, https://github.com/mtillman14/zotero_utils
Author-email: Mitchell Tillman <mtillman14@gmail.com>
Requires-Dist: matplotlib
Requires-Dist: pandas
Requires-Dist: plotly
Requires-Dist: typer
